anet_common/__init__.py
anet_common/conf.py
anet_common/errors.json
anet_common/middleware.py
anet_common/drf/__init__.py
anet_common/drf/exceptions.py
anet_common/drf/pagination.py
anet_common/drf/renderers.py
anet_common/spectacular/__init__.py
anet_common/spectacular/schema.py
anet_common-0.1.5.dist-info/METADATA
anet_common-0.1.5.dist-info/WHEEL
anet_common-0.1.5.dist-info/top_level.txt
anet_common-0.1.5.dist-info/RECORD
