Metadata-Version: 2.4
Name: anet-common
Version: 0.1.5
Summary: Common utilities, settings, and contracts for Anet Microservices (Django/DRF)
Home-page: https://github.com/murodalidev/anet-common/
Author: Murodali Narzullaev
Author-email: murodalinarzullaevofficial@gmail.uz
License: MIT
Keywords: django,drf,microservices,utilities,common
Classifier: Development Status :: 3 - Alpha
Classifier: Environment :: Web Environment
Classifier: Framework :: Django
Classifier: Framework :: Django :: 5.0
Classifier: Intended Audience :: Developers
Classifier: License :: OSI Approved :: MIT License
Classifier: Operating System :: OS Independent
Classifier: Programming Language :: Python :: 3
Classifier: Programming Language :: Python :: 3.10
Classifier: Programming Language :: Python :: 3.11
Classifier: Topic :: Internet :: WWW/HTTP
Classifier: Topic :: Internet :: WWW/HTTP :: Dynamic Content
Requires-Python: >=3.10
Requires-Dist: Django>=5.2
Requires-Dist: djangorestframework==3.16.1
Requires-Dist: drf-spectacular==0.29.0
Requires-Dist: django-modeltranslation==0.19.19
Requires-Dist: djangorestframework-camel-case>=1.4.2
Dynamic: author
Dynamic: author-email
Dynamic: classifier
Dynamic: description
Dynamic: description-content-type
Dynamic: home-page
Dynamic: keywords
Dynamic: license
Dynamic: requires-dist
Dynamic: requires-python
Dynamic: summary
